{
  "slug": "immortal-science-and-technology",
  "title": "Immortal Science and Technology",
  "author": "",
  "description": "Immortal Science and Technology Manhua Su Jingyao, a modern high IQ student and technology expert, died suddenly due to a blast of artificial intelligence program. His soul penetrated into the fantasy world of cultivating immortals. He signed a contract with the girl Yin Ling in the mysterious pendant, and began his life of cultivating immortals in another world. With modern knowledge, he has developed a technology product that shocked everyone’s attention. Versailles has transformed a group of powerful people, met five confidantes, and brought the beauty to the pinnacle of life. First place in the strong list; led the academy to participate in the hegemony competition and became the first person in the Southern Territory 100 academies; led the sect to resist the ultimate boss, and eventually became a mainland legend Keji Daxian Zong The Great Immortal Ancestor of Science and Technology 科技大仙宗",
  "thumbnail": "https://manhuaus.com/wp-content/uploads/2022/01/i364051.jpg",
  "url": "https://manhuaus.com/manga/immortal-science-and-technology/",
  "rank": "N/A, it has 16.9K monthly views",
  "alternative_titles": [
    "The Great Immortal Ancestor of Science and Technology",
    "科技大仙宗",
    "Keji Daxian Zong",
    "Immortal Science and Technology"
  ],
  "genres": [
    "Action",
    "Adventure",
    "Drama",
    "Fantasy",
    "Historical",
    "Martial Arts",
    "Shounen"
  ],
  "status": "Completed",
  "bookmarked": 13,
  "total_chapters": 2,
  "chapters": [
    {
      "number": 1,
      "title": "Chapter 1",
      "release_date": "05-06-2022",
      "pages": [
        "https://img.manhuaus.com/immortal-science-and-technology/chapter-1/001.jpg",
        "https://img.manhuaus.com/immortal-science-and-technology/chapter-1/002.jpg",
        "https://img.manhuaus.com/immortal-science-and-technology/chapter-1/003.jpg",
        "https://img.manhuaus.com/immortal-science-and-technology/chapter-1/004.jpg",
        "https://img.manhuaus.com/immortal-science-and-technology/chapter-1/005.jpg",
        "https://img.manhuaus.com/immortal-science-and-technology/chapter-1/006.jpg",
        "https://img.manhuaus.com/immortal-science-and-technology/chapter-1/007.jpg",
        "https://img.manhuaus.com/immortal-science-and-technology/chapter-1/008.jpg",
        "https://img.manhuaus.com/immortal-science-and-technology/chapter-1/009.jpg"
      ]
    },
    {
      "number": 2,
      "title": "Chapter 2",
      "release_date": "05-06-2022",
      "pages": [
        "https://img.manhuaus.com/immortal-science-and-technology/chapter-2/001.jpg",
        "https://img.manhuaus.com/immortal-science-and-technology/chapter-2/002.jpg",
        "https://img.manhuaus.com/immortal-science-and-technology/chapter-2/003.jpg",
        "https://img.manhuaus.com/immortal-science-and-technology/chapter-2/004.jpg",
        "https://img.manhuaus.com/immortal-science-and-technology/chapter-2/005.jpg",
        "https://img.manhuaus.com/immortal-science-and-technology/chapter-2/006.jpg",
        "https://img.manhuaus.com/immortal-science-and-technology/chapter-2/007.jpg",
        "https://img.manhuaus.com/immortal-science-and-technology/chapter-2/008.jpg",
        "https://img.manhuaus.com/immortal-science-and-technology/chapter-2/009.jpg"
      ]
    }
  ]
}